{
  "id": "snapshot_1766151634811_orjjjxvfv",
  "approvalId": "approval_1766151634372_232mqniop",
  "approvalTitle": "Design: Inventory Components Documentation Pages",
  "version": 1,
  "timestamp": "2025-12-19T13:40:34.811Z",
  "trigger": "initial",
  "status": "pending",
  "content": "# Design Document\n\n## Overview\n\nThis design outlines the implementation of 10 comprehensive documentation pages for inventory management components in the @apps/admin application. The implementation follows the established documentation patterns used throughout the admin app, ensuring consistency with existing component documentation pages like Card, Badge, and other AegisX UI components.\n\nEach documentation page will follow the standard 5-tab structure (Overview, Examples, API, Tokens, Guidelines) and leverage existing documentation helper components (DocHeader, LivePreview, CodeTabs, ComponentTokens). The pages will be organized under a new \"Inventory\" category in the navigation system, with proper routing and lazy-loading configuration.\n\n## Steering Document Alignment\n\n### Technical Standards (tech.md)\n\nSince no steering documents exist, this design follows the technical patterns observed in the existing codebase:\n\n- **Angular Standalone Components**: All documentation pages use standalone component architecture\n- **Lazy Loading**: Routes use dynamic imports for code splitting and performance\n- **TypeScript Strict Mode**: All code adheres to strict type checking\n- **Material Design**: Consistent use of Angular Material components\n- **Design Tokens**: Adherence to AegisX design token system (CSS variables)\n- **Accessibility**: WCAG 2.1 AA compliance throughout\n\n### Project Structure (structure.md)\n\nFollowing the established admin app structure:\n\n```\napps/admin/src/app/\n├── pages/docs/components/aegisx/\n│   └── inventory/                    # New category directory\n│       ├── stock-level/\n│       ├── stock-alert-panel/\n│       ├── location-picker/\n│       ├── quantity-input/\n│       ├── barcode-scanner/\n│       ├── batch-selector/\n│       ├── expiry-badge/\n│       ├── stock-movement-timeline/\n│       ├── transfer-wizard/\n│       └── variant-selector/\n├── routes/docs/components-aegisx/\n│   └── inventory.routes.ts           # New routes file\n└── config/\n    └── navigation.config.ts          # Update with inventory items\n```\n\n## Code Reuse Analysis\n\n### Existing Components to Leverage\n\n1. **Doc Helper Components** (`apps/admin/src/app/components/docs/`):\n   - `DocHeaderComponent`: Page header with breadcrumbs, title, description, import statement\n   - `LivePreviewComponent`: Live component demonstration container with customizable backgrounds\n   - `CodeTabsComponent`: Syntax-highlighted code display with copy functionality\n   - `ComponentTokensComponent`: Design token display system\n   - `CodePreviewComponent`: Additional code preview utilities\n\n2. **Documentation Types** (`apps/admin/src/app/types/docs.types.ts`):\n   - `CodeTab`: Interface for multi-language code examples\n   - `ComponentToken`: Interface for design token documentation\n   - `BreadcrumbItem`: Navigation breadcrumb structure\n   - `ComponentStatus`: Status badge types (stable/beta/experimental)\n\n3. **Existing Route Patterns**:\n   - Reuse lazy-loading pattern from `data-display.routes.ts`, `forms.routes.ts`\n   - Follow consistent route data structure with title and description\n   - Apply same path naming conventions (kebab-case)\n\n4. **Navigation Configuration Pattern**:\n   - Extend `DOCS_NAVIGATION` in `navigation.config.ts`\n   - Use existing navigation item structure with id, title, icon, link\n   - Follow category grouping conventions\n\n### Integration Points\n\n1. **Routing System** (`apps/admin/src/app/app.routes.ts`):\n   - Integrate `INVENTORY_ROUTES` into `COMPONENTS_AEGISX_ROUTES`\n   - Maintain consistent route hierarchy: `/docs/components/aegisx/inventory/{component}`\n\n2. **Navigation System** (`apps/admin/src/app/config/navigation.config.ts`):\n   - Add \"Inventory\" section under Components category\n   - Include all 10 components with appropriate Material icons\n   - Maintain alphabetical ordering within sections\n\n3. **Component Library** (`@aegisx/ui`):\n   - Import all 10 inventory components from `libs/aegisx-ui/src/lib/components/inventory/`\n   - Reference component type definitions for API documentation\n   - Use actual component instances in live previews\n\n## Architecture\n\n### Modular Design Principles\n\nEach documentation page follows these principles:\n\n- **Single File Responsibility**: Each component doc file handles documentation for exactly one inventory component\n- **Component Isolation**: Documentation pages are independent, standalone modules with no cross-dependencies\n- **Service Layer Separation**: Documentation logic (code examples, token definitions) separated from presentation (template)\n- **Utility Modularity**: Shared utilities accessed through doc helper components, not duplicated\n\n### Architecture Diagram\n\n```mermaid\ngraph TD\n    A[Admin App Routes] --> B[Inventory Routes Module]\n    B --> C1[Stock Level Doc Component]\n    B --> C2[Stock Alert Panel Doc Component]\n    B --> C3[Location Picker Doc Component]\n    B --> C4[Quantity Input Doc Component]\n    B --> C5[Barcode Scanner Doc Component]\n    B --> C6[Batch Selector Doc Component]\n    B --> C7[Expiry Badge Doc Component]\n    B --> C8[Stock Movement Timeline Doc Component]\n    B --> C9[Transfer Wizard Doc Component]\n    B --> C10[Variant Selector Doc Component]\n\n    C1 --> D[Doc Helper Components]\n    C2 --> D\n    C3 --> D\n    C4 --> D\n    C5 --> D\n    C6 --> D\n    C7 --> D\n    C8 --> D\n    C9 --> D\n    C10 --> D\n\n    D --> D1[DocHeader]\n    D --> D2[LivePreview]\n    D --> D3[CodeTabs]\n    D --> D4[ComponentTokens]\n\n    C1 --> E[@aegisx/ui Inventory Components]\n    C2 --> E\n    C3 --> E\n    C4 --> E\n    C5 --> E\n    C6 --> E\n    C7 --> E\n    C8 --> E\n    C9 --> E\n    C10 --> E\n```\n\n### Component Documentation Page Structure\n\nEach documentation component follows this standard structure:\n\n```typescript\n@Component({\n  selector: 'ax-[component]-doc',\n  standalone: true,\n  imports: [\n    CommonModule,\n    MatTabsModule,\n    MatIconModule,\n    MatButtonModule,\n    MatCardModule,\n    // ... other Material modules as needed\n    [InventoryComponent],        // The component being documented\n    DocHeaderComponent,\n    LivePreviewComponent,\n    CodeTabsComponent,\n    ComponentTokensComponent,\n  ],\n  templateUrl: './[component]-doc.component.html',\n  styleUrls: ['./[component]-doc.component.scss']\n})\nexport class [Component]DocComponent {\n  // Breadcrumb navigation\n  breadcrumbs: BreadcrumbItem[] = [\n    { label: 'Documentation', link: '/docs' },\n    { label: 'Components', link: '/docs/components' },\n    { label: 'Inventory', link: '/docs/components/aegisx/inventory' },\n    { label: '[Component Name]' }\n  ];\n\n  // Code examples for each section\n  basicUsageCode: CodeTab[] = [...];\n  variantsCode: CodeTab[] = [...];\n  exampleCode: CodeTab[] = [...];\n\n  // Design tokens\n  componentTokens: ComponentToken[] = [...];\n\n  // Component status\n  status: ComponentStatus = 'stable';\n}\n```\n\n## Components and Interfaces\n\n### Component 1: Stock Level Documentation Component\n\n- **Purpose:** Document the Stock Level component showing progress bar with color-coded zones\n- **File:** `apps/admin/src/app/pages/docs/components/aegisx/inventory/stock-level/stock-level-doc.component.ts`\n- **Interfaces:**\n  - Implements standard 5-tab documentation structure\n  - Provides code examples for traffic-light and gradient color schemes\n  - Documents size variants (sm/md/lg)\n- **Dependencies:** MatTabsModule, DocHelper components, AxStockLevelComponent\n- **Reuses:** Existing DocHeader, LivePreview, CodeTabs patterns from Card/Badge docs\n\n### Component 2: Stock Alert Panel Documentation Component\n\n- **Purpose:** Document the Stock Alert Panel for displaying inventory alerts with filtering\n- **File:** `apps/admin/src/app/pages/docs/components/aegisx/inventory/stock-alert-panel/stock-alert-panel-doc.component.ts`\n- **Interfaces:**\n  - Shows alert severity levels (critical/warning/info)\n  - Demonstrates filtering and action handling\n  - WebSocket integration examples\n- **Dependencies:** MatTabsModule, DocHelper components, AxStockAlertPanelComponent\n- **Reuses:** Alert-style documentation patterns, table components for API reference\n\n### Component 3: Location Picker Documentation Component\n\n- **Purpose:** Document the Location Picker tree view component\n- **File:** `apps/admin/src/app/pages/docs/components/aegisx/inventory/location-picker/location-picker-doc.component.ts`\n- **Interfaces:**\n  - Tree view navigation examples\n  - Search and favorites functionality\n  - Multi-select mode demonstrations\n- **Dependencies:** MatTabsModule, MatTreeModule, DocHelper components, AxLocationPickerComponent\n- **Reuses:** Tree-based component documentation patterns\n\n### Component 4: Quantity Input Documentation Component\n\n- **Purpose:** Document the Quantity Input numeric control component\n- **File:** `apps/admin/src/app/pages/docs/components/aegisx/inventory/quantity-input/quantity-input-doc.component.ts`\n- **Interfaces:**\n  - Basic increment/decrement controls\n  - Min/max validation examples\n  - Step increments and decimal support\n- **Dependencies:** MatTabsModule, MatFormFieldModule, DocHelper components, AxQuantityInputComponent\n- **Reuses:** Form input documentation patterns from date-picker/file-upload docs\n\n### Component 5: Barcode Scanner Documentation Component\n\n- **Purpose:** Document the Barcode Scanner camera integration component\n- **File:** `apps/admin/src/app/pages/docs/components/aegisx/inventory/barcode-scanner/barcode-scanner-doc.component.ts`\n- **Interfaces:**\n  - Camera scanning mode examples\n  - Manual entry fallback\n  - Supported barcode formats\n- **Dependencies:** MatTabsModule, DocHelper components, AxBarcodeScannerComponent\n- **Reuses:** Interactive component documentation patterns\n\n### Component 6: Batch Selector Documentation Component\n\n- **Purpose:** Document the Batch Selector FIFO/FEFO/LIFO component\n- **File:** `apps/admin/src/app/pages/docs/components/aegisx/inventory/batch-selector/batch-selector-doc.component.ts`\n- **Interfaces:**\n  - FIFO/FEFO/LIFO strategy examples\n  - Batch selection with quantities\n  - Expiry tracking integration\n- **Dependencies:** MatTabsModule, MatRadioModule, DocHelper components, AxBatchSelectorComponent\n- **Reuses:** Selection component documentation patterns\n\n### Component 7: Expiry Badge Documentation Component\n\n- **Purpose:** Document the Expiry Badge status indicator component\n- **File:** `apps/admin/src/app/pages/docs/components/aegisx/inventory/expiry-badge/expiry-badge-doc.component.ts`\n- **Interfaces:**\n  - Color-coded status examples\n  - Size and variant options\n  - Compact mode for tables\n- **Dependencies:** MatTabsModule, DocHelper components, AxExpiryBadgeComponent\n- **Reuses:** Badge documentation patterns from existing badge-doc component\n\n### Component 8: Stock Movement Timeline Documentation Component\n\n- **Purpose:** Document the Stock Movement Timeline history component\n- **File:** `apps/admin/src/app/pages/docs/components/aegisx/inventory/stock-movement-timeline/stock-movement-timeline-doc.component.ts`\n- **Interfaces:**\n  - Timeline view with Chart.js integration\n  - Filtering and grouping options\n  - Export functionality (PDF/Excel)\n- **Dependencies:** MatTabsModule, DocHelper components, AxStockMovementTimelineComponent\n- **Reuses:** Chart component documentation patterns, data display patterns\n\n### Component 9: Transfer Wizard Documentation Component\n\n- **Purpose:** Document the Transfer Wizard multi-step form component\n- **File:** `apps/admin/src/app/pages/docs/components/aegisx/inventory/transfer-wizard/transfer-wizard-doc.component.ts`\n- **Interfaces:**\n  - 5-step workflow demonstration\n  - Form validation at each step\n  - Draft save/load functionality\n- **Dependencies:** MatTabsModule, MatStepperModule, DocHelper components, AxTransferWizardComponent\n- **Reuses:** Stepper/wizard documentation patterns\n\n### Component 10: Variant Selector Documentation Component\n\n- **Purpose:** Document the Variant Selector product variant component\n- **File:** `apps/admin/src/app/pages/docs/components/aegisx/inventory/variant-selector/variant-selector-doc.component.ts`\n- **Interfaces:**\n  - Grid/list/compact layout modes\n  - Multi-dimensional variant selection\n  - Stock availability display\n- **Dependencies:** MatTabsModule, MatGridListModule, DocHelper components, AxVariantSelectorComponent\n- **Reuses:** Selection and filtering documentation patterns\n\n## Data Models\n\n### CodeTab Model (Existing - Reused)\n```typescript\ninterface CodeTab {\n  label: string;                    // Tab label (e.g., \"HTML\", \"TypeScript\")\n  code: string;                     // Code content\n  language: 'typescript' | 'html' | 'scss' | 'bash' | 'json' | 'preview';\n}\n```\n\n**Usage:** Used in all documentation components to provide multi-language code examples\n\n### ComponentToken Model (Existing - Reused)\n```typescript\ninterface ComponentToken {\n  category: string;                 // Token category (e.g., \"Colors\", \"Spacing\")\n  cssVar: string;                   // CSS variable name (e.g., \"--ax-brand-default\")\n  usage: string;                    // Description of usage\n  value?: string;                   // Optional default value\n}\n```\n\n**Usage:** Documents design tokens used by each inventory component\n\n### BreadcrumbItem Model (Existing - Reused)\n```typescript\ninterface BreadcrumbItem {\n  label: string;                    // Breadcrumb text\n  link?: string;                    // Optional navigation link\n}\n```\n\n**Usage:** Navigation breadcrumbs in doc-header component\n\n### DocumentationPageConfig (New - Internal)\n```typescript\ninterface DocumentationPageConfig {\n  component: {\n    name: string;                   // Component name for display\n    selector: string;               // Component HTML selector\n    importPath: string;             // Import path from @aegisx/ui\n    status: ComponentStatus;        // stable | beta | experimental | deprecated\n    version?: string;               // Optional version number\n  };\n  sections: {\n    overview: {\n      basicUsage: CodeTab[];\n      variants?: CodeTab[];\n      sizes?: CodeTab[];\n      states?: CodeTab[];\n    };\n    examples: {\n      title: string;\n      description: string;\n      code: CodeTab[];\n    }[];\n    api: {\n      inputs: APIProperty[];\n      outputs: APIProperty[];\n      methods?: APIProperty[];\n    };\n    tokens: ComponentToken[];\n    guidelines: {\n      dos: string[];\n      donts: string[];\n      accessibility: string[];\n    };\n  };\n}\n```\n\n**Usage:** Internal configuration model for organizing documentation content\n\n### APIProperty Model (New - Internal)\n```typescript\ninterface APIProperty {\n  name: string;                     // Property/event/method name\n  type: string;                     // TypeScript type\n  default?: string;                 // Default value (if applicable)\n  description: string;              // Description of purpose and usage\n  required?: boolean;               // Whether required (for inputs)\n}\n```\n\n**Usage:** Documents component inputs, outputs, and methods in API tables\n\n## Error Handling\n\n### Error Scenarios\n\n1. **Component Import Failure**\n   - **Handling:** Wrap component imports in try-catch, display error message in live preview\n   - **User Impact:** User sees \"Component failed to load\" with error details instead of broken page\n   - **Implementation:** Use Angular error boundaries or ngOnInit error handling\n\n2. **Code Syntax Highlighting Failure**\n   - **Handling:** Fallback to plain text display if Prism.js fails\n   - **User Impact:** Code is still readable, just without syntax highlighting\n   - **Implementation:** Error handling in CodeTabsComponent\n\n3. **Route Navigation Error**\n   - **Handling:** Redirect to 404 page or documentation home if route doesn't exist\n   - **User Impact:** Clear error message with navigation options\n   - **Implementation:** Angular route guards and error handling\n\n4. **Live Preview Rendering Error**\n   - **Handling:** Catch component errors, display error state with code example\n   - **User Impact:** User can still see code even if live preview fails\n   - **Implementation:** Error boundaries in LivePreviewComponent\n\n5. **Invalid Component Configuration**\n   - **Handling:** Validate example data, show warning in development mode\n   - **User Impact:** Prevents broken examples from being displayed\n   - **Implementation:** TypeScript validation + runtime checks\n\n## Routing Configuration\n\n### Route Structure\n\nFile: `apps/admin/src/app/routes/docs/components-aegisx/inventory.routes.ts`\n\n```typescript\nimport { Route } from '@angular/router';\n\nexport const INVENTORY_ROUTES: Route[] = [\n  {\n    path: 'inventory/stock-level',\n    loadComponent: () =>\n      import('../../../pages/docs/components/aegisx/inventory/stock-level/stock-level-doc.component')\n        .then((m) => m.StockLevelDocComponent),\n    data: {\n      title: 'Stock Level Component',\n      description: 'Progress bar indicator for inventory levels with color-coded zones',\n    },\n  },\n  {\n    path: 'inventory/stock-alert-panel',\n    loadComponent: () =>\n      import('../../../pages/docs/components/aegisx/inventory/stock-alert-panel/stock-alert-panel-doc.component')\n        .then((m) => m.StockAlertPanelDocComponent),\n    data: {\n      title: 'Stock Alert Panel Component',\n      description: 'Alert management panel with filtering and action handling',\n    },\n  },\n  // ... 8 more routes following same pattern\n];\n```\n\n### Integration with Main Routes\n\nFile: `apps/admin/src/app/routes/docs/components-aegisx/index.ts`\n\n```typescript\nimport { INVENTORY_ROUTES } from './inventory.routes';\n\nexport const COMPONENTS_AEGISX_ROUTES: Route[] = [\n  ...DATA_DISPLAY_ROUTES,\n  ...FORMS_ROUTES,\n  ...FEEDBACK_ROUTES,\n  ...NAVIGATION_ROUTES,\n  ...LAYOUT_ROUTES,\n  ...UTILITIES_ROUTES,\n  ...DASHBOARD_ROUTES,\n  ...AUTH_ROUTES,\n  ...UI_BLOCKS_ROUTES,\n  ...INVENTORY_ROUTES,        // New addition\n];\n```\n\n## Navigation Configuration\n\n### Navigation Items\n\nFile: `apps/admin/src/app/config/navigation.config.ts`\n\nAdd to `DOCS_NAVIGATION` under Components section:\n\n```typescript\n{\n  id: 'components-inventory',\n  title: 'Inventory',\n  type: 'collapsable',\n  icon: 'inventory_2',\n  children: [\n    {\n      id: 'barcode-scanner',\n      title: 'Barcode Scanner',\n      type: 'item',\n      icon: 'qr_code_scanner',\n      link: '/docs/components/aegisx/inventory/barcode-scanner',\n    },\n    {\n      id: 'batch-selector',\n      title: 'Batch Selector',\n      type: 'item',\n      icon: 'widgets',\n      link: '/docs/components/aegisx/inventory/batch-selector',\n    },\n    {\n      id: 'expiry-badge',\n      title: 'Expiry Badge',\n      type: 'item',\n      icon: 'event_busy',\n      link: '/docs/components/aegisx/inventory/expiry-badge',\n    },\n    {\n      id: 'location-picker',\n      title: 'Location Picker',\n      type: 'item',\n      icon: 'place',\n      link: '/docs/components/aegisx/inventory/location-picker',\n    },\n    {\n      id: 'quantity-input',\n      title: 'Quantity Input',\n      type: 'item',\n      icon: 'add_circle',\n      link: '/docs/components/aegisx/inventory/quantity-input',\n    },\n    {\n      id: 'stock-alert-panel',\n      title: 'Stock Alert Panel',\n      type: 'item',\n      icon: 'notifications',\n      link: '/docs/components/aegisx/inventory/stock-alert-panel',\n    },\n    {\n      id: 'stock-level',\n      title: 'Stock Level',\n      type: 'item',\n      icon: 'trending_up',\n      link: '/docs/components/aegisx/inventory/stock-level',\n    },\n    {\n      id: 'stock-movement-timeline',\n      title: 'Stock Movement Timeline',\n      type: 'item',\n      icon: 'timeline',\n      link: '/docs/components/aegisx/inventory/stock-movement-timeline',\n    },\n    {\n      id: 'transfer-wizard',\n      title: 'Transfer Wizard',\n      type: 'item',\n      icon: 'swap_horiz',\n      link: '/docs/components/aegisx/inventory/transfer-wizard',\n    },\n    {\n      id: 'variant-selector',\n      title: 'Variant Selector',\n      type: 'item',\n      icon: 'tune',\n      link: '/docs/components/aegisx/inventory/variant-selector',\n    },\n  ],\n}\n```\n\n## Template Structure\n\n### Standard 5-Tab Documentation Template\n\nEach component documentation page uses this HTML template structure:\n\n```html\n<!-- Doc Header -->\n<ax-doc-header\n  [breadcrumbs]=\"breadcrumbs\"\n  [title]=\"componentName\"\n  [description]=\"componentDescription\"\n  [status]=\"status\"\n  [importStatement]=\"importStatement\"\n  [quickLinks]=\"quickLinks\">\n</ax-doc-header>\n\n<!-- Tabbed Content -->\n<mat-tab-group class=\"component-doc__tabs\">\n\n  <!-- Tab 1: Overview -->\n  <mat-tab label=\"Overview\">\n    <section id=\"basic-usage\">\n      <h2>Basic Usage</h2>\n      <ax-live-preview variant=\"bordered\">\n        <!-- Live component example -->\n      </ax-live-preview>\n      <ax-code-tabs [tabs]=\"basicUsageCode\"></ax-code-tabs>\n    </section>\n\n    <section id=\"variants\">\n      <h2>Variants</h2>\n      <!-- Multiple live examples with code -->\n    </section>\n\n    <!-- Additional sections as needed -->\n  </mat-tab>\n\n  <!-- Tab 2: Examples -->\n  <mat-tab label=\"Examples\">\n    <section id=\"example-1\">\n      <h2>Example Title</h2>\n      <p>Description of use case</p>\n      <ax-live-preview>\n        <!-- Real-world example -->\n      </ax-live-preview>\n      <ax-code-tabs [tabs]=\"exampleCode\"></ax-code-tabs>\n    </section>\n\n    <!-- 3-5 examples total -->\n  </mat-tab>\n\n  <!-- Tab 3: API -->\n  <mat-tab label=\"API\">\n    <section id=\"properties\">\n      <h2>Input Properties</h2>\n      <table class=\"api-table\">\n        <thead>\n          <tr>\n            <th>Property</th>\n            <th>Type</th>\n            <th>Default</th>\n            <th>Description</th>\n          </tr>\n        </thead>\n        <tbody>\n          <!-- Property rows -->\n        </tbody>\n      </table>\n    </section>\n\n    <section id=\"events\">\n      <h2>Output Events</h2>\n      <table class=\"api-table\">\n        <!-- Event rows -->\n      </table>\n    </section>\n\n    <section id=\"methods\">\n      <h2>Methods</h2>\n      <table class=\"api-table\">\n        <!-- Method rows -->\n      </table>\n    </section>\n  </mat-tab>\n\n  <!-- Tab 4: Tokens -->\n  <mat-tab label=\"Tokens\">\n    <ax-component-tokens [tokens]=\"componentTokens\"></ax-component-tokens>\n  </mat-tab>\n\n  <!-- Tab 5: Guidelines -->\n  <mat-tab label=\"Guidelines\">\n    <section id=\"dos-donts\">\n      <h2>Do's and Don'ts</h2>\n      <div class=\"guidelines-grid\">\n        <div class=\"guideline guideline--do\">\n          <!-- Do examples -->\n        </div>\n        <div class=\"guideline guideline--dont\">\n          <!-- Don't examples -->\n        </div>\n      </div>\n    </section>\n\n    <section id=\"accessibility\">\n      <h2>Accessibility</h2>\n      <ul>\n        <!-- A11y guidelines -->\n      </ul>\n    </section>\n  </mat-tab>\n</mat-tab-group>\n```\n\n## Testing Strategy\n\n### Unit Testing\n\n**Approach:** Test each documentation component in isolation\n\n**Key Components to Test:**\n1. Component initialization (breadcrumbs, code examples, tokens)\n2. Tab rendering and switching\n3. Code example data structure validation\n4. API table generation from property definitions\n5. Import statement generation accuracy\n\n**Test Files:** Create `[component]-doc.component.spec.ts` for each documentation component\n\n**Example Test Cases:**\n```typescript\ndescribe('StockLevelDocComponent', () => {\n  it('should create breadcrumb navigation correctly', () => {\n    // Test breadcrumb structure\n  });\n\n  it('should display all 5 tabs', () => {\n    // Test tab presence\n  });\n\n  it('should have valid code examples', () => {\n    // Test code tab structure\n  });\n\n  it('should document all component inputs', () => {\n    // Test API documentation completeness\n  });\n});\n```\n\n### Integration Testing\n\n**Approach:** Test routing and navigation integration\n\n**Key Flows to Test:**\n1. Navigation from components menu to documentation page\n2. Route lazy-loading and component initialization\n3. Breadcrumb navigation links\n4. Quick links within documentation\n5. Code copy functionality\n6. Tab switching and deep linking\n\n**Test Scenarios:**\n- Navigate to `/docs/components/aegisx/inventory/stock-level`\n- Click breadcrumb to navigate back to components overview\n- Click quick link to jump to API section\n- Copy code example to clipboard\n- Switch between tabs and verify content loads\n\n### End-to-End Testing\n\n**Approach:** Test complete user documentation exploration workflows\n\n**User Scenarios to Test:**\n\n**Scenario 1: Discover and Learn About Component**\n1. User opens admin app\n2. Navigates to Documentation > Components > Inventory\n3. Clicks \"Stock Level\" from navigation\n4. Views Overview tab examples\n5. Switches to Examples tab to see real-world usage\n6. Checks API tab for property reference\n7. Copies code example to clipboard\n8. Reviews Guidelines for accessibility best practices\n\n**Scenario 2: Compare Multiple Inventory Components**\n1. User opens Stock Level documentation\n2. Notes pattern for progress indicators\n3. Navigates to Stock Movement Timeline\n4. Compares Chart.js integration approach\n5. Returns to Stock Level using breadcrumbs\n6. Switches between components using navigation menu\n\n**Scenario 3: Mobile Documentation Access**\n1. User opens documentation on mobile device\n2. Navigation menu collapses appropriately\n3. Code examples remain readable\n4. Live previews scale to viewport\n5. Tables scroll horizontally on small screens\n6. Tab interface adapts to touch\n\n**E2E Test Tools:**\n- Playwright or Cypress for automated testing\n- Manual testing checklist for visual verification\n- Accessibility audit using axe-core\n\n## File Organization Summary\n\n```\napps/admin/src/app/\n├── pages/docs/components/aegisx/inventory/\n│   ├── barcode-scanner/\n│   │   ├── barcode-scanner-doc.component.ts\n│   │   ├── barcode-scanner-doc.component.html\n│   │   ├── barcode-scanner-doc.component.scss\n│   │   └── barcode-scanner-doc.component.spec.ts\n│   ├── batch-selector/\n│   │   ├── batch-selector-doc.component.ts\n│   │   ├── batch-selector-doc.component.html\n│   │   ├── batch-selector-doc.component.scss\n│   │   └── batch-selector-doc.component.spec.ts\n│   ├── expiry-badge/\n│   │   ├── expiry-badge-doc.component.ts\n│   │   ├── expiry-badge-doc.component.html\n│   │   ├── expiry-badge-doc.component.scss\n│   │   └── expiry-badge-doc.component.spec.ts\n│   ├── location-picker/\n│   │   ├── location-picker-doc.component.ts\n│   │   ├── location-picker-doc.component.html\n│   │   ├── location-picker-doc.component.scss\n│   │   └── location-picker-doc.component.spec.ts\n│   ├── quantity-input/\n│   │   ├── quantity-input-doc.component.ts\n│   │   ├── quantity-input-doc.component.html\n│   │   ├── quantity-input-doc.component.scss\n│   │   └── quantity-input-doc.component.spec.ts\n│   ├── stock-alert-panel/\n│   │   ├── stock-alert-panel-doc.component.ts\n│   │   ├── stock-alert-panel-doc.component.html\n│   │   ├── stock-alert-panel-doc.component.scss\n│   │   └── stock-alert-panel-doc.component.spec.ts\n│   ├── stock-level/\n│   │   ├── stock-level-doc.component.ts\n│   │   ├── stock-level-doc.component.html\n│   │   ├── stock-level-doc.component.scss\n│   │   └── stock-level-doc.component.spec.ts\n│   ├── stock-movement-timeline/\n│   │   ├── stock-movement-timeline-doc.component.ts\n│   │   ├── stock-movement-timeline-doc.component.html\n│   │   ├── stock-movement-timeline-doc.component.scss\n│   │   └── stock-movement-timeline-doc.component.spec.ts\n│   ├── transfer-wizard/\n│   │   ├── transfer-wizard-doc.component.ts\n│   │   ├── transfer-wizard-doc.component.html\n│   │   ├── transfer-wizard-doc.component.scss\n│   │   └── transfer-wizard-doc.component.spec.ts\n│   └── variant-selector/\n│       ├── variant-selector-doc.component.ts\n│       ├── variant-selector-doc.component.html\n│       ├── variant-selector-doc.component.scss\n│       └── variant-selector-doc.component.spec.ts\n├── routes/docs/components-aegisx/\n│   └── inventory.routes.ts                    # New routes file\n└── config/\n    └── navigation.config.ts                   # Updated with inventory section\n```\n\n**Total Files to Create:** 44 files (40 component files + 1 routes file + 3 config updates)\n\n## Implementation Phases\n\nThis design will be implemented in phases aligned with the task breakdown:\n\n**Phase 1: Infrastructure Setup**\n- Create inventory directory structure\n- Create and configure inventory.routes.ts\n- Update navigation.config.ts\n- Update main routes integration\n\n**Phase 2: Component Documentation (Batch 1: Simple Components)**\n- Stock Level\n- Expiry Badge\n- Quantity Input\n\n**Phase 3: Component Documentation (Batch 2: Interactive Components)**\n- Location Picker\n- Barcode Scanner\n- Batch Selector\n\n**Phase 4: Component Documentation (Batch 3: Complex Components)**\n- Stock Alert Panel\n- Stock Movement Timeline\n- Transfer Wizard\n- Variant Selector\n\n**Phase 5: Testing and Polish**\n- Unit tests for all documentation components\n- Integration tests for routing\n- E2E tests for user workflows\n- Accessibility audit and fixes\n- Documentation review and refinement\n",
  "fileStats": {
    "size": 29446,
    "lines": 864,
    "lastModified": "2025-12-19T13:38:24.275Z"
  },
  "comments": []
}
